collagist/__init__.py
collagist/vanilla.py
collagist-0.1.0.dist-info/LICENSE
collagist-0.1.0.dist-info/METADATA
collagist-0.1.0.dist-info/WHEEL
collagist-0.1.0.dist-info/top_level.txt
collagist-0.1.0.dist-info/RECORD
